request_profiler/__init__.py
request_profiler/admin.py
request_profiler/apps.py
request_profiler/management/__init__.py
request_profiler/management/commands/__init__.py
request_profiler/management/commands/truncate_request_profiler_logs.py
request_profiler/middleware.py
request_profiler/migrations/0001_initial.py
request_profiler/migrations/0002_profilingrecord_http_referer.py
request_profiler/migrations/0003_profilingrecord_query_string.py
request_profiler/migrations/0004_profilingrecord_query_count.py
request_profiler/migrations/0005_alter_profilingrecord_id_alter_ruleset_id.py
request_profiler/migrations/__init__.py
request_profiler/models.py
request_profiler/settings.py
request_profiler/signals.py
django_request_profiler-1.1.dist-info/LICENSE
django_request_profiler-1.1.dist-info/METADATA
django_request_profiler-1.1.dist-info/WHEEL
django_request_profiler-1.1.dist-info/RECORD
