Metadata-Version: 2.1
Name: django-request-profiler
Version: 1.1
Summary: A simple Django project profiler for timing HTTP requests.
Home-page: https://github.com/yunojuno/django-request-profiler
License: MIT
Author: YunoJuno
Author-email: code@yunojuno.com
Requires-Python: >=3.9,<4.0
Classifier: Environment :: Web Environment
Classifier: Framework :: Django
Classifier: Framework :: Django :: 3.2
Classifier: Framework :: Django :: 4.0
Classifier: Framework :: Django :: 4.1
Classifier: Framework :: Django :: 5.0
Classifier: Intended Audience :: Developers
Classifier: License :: OSI Approved :: MIT License
Classifier: Operating System :: OS Independent
Classifier: Programming Language :: Python :: 3
Classifier: Programming Language :: Python :: 3.9
Classifier: Programming Language :: Python :: 3.10
Classifier: Programming Language :: Python :: 3.11
Classifier: Programming Language :: Python :: 3 :: Only
Classifier: Programming Language :: Python :: 3.12
Requires-Dist: django (>=3.2,<6.0)
Project-URL: Repository, https://github.com/yunojuno/django-request-profiler
